primoscm/__init__.py
primoscm-1.0.dist-info/LICENSE
primoscm-1.0.dist-info/METADATA
primoscm-1.0.dist-info/WHEEL
primoscm-1.0.dist-info/top_level.txt
primoscm-1.0.dist-info/RECORD
