Metadata-Version: 2.1
Name: primoscm
Version: 1.0
Summary: Función para calcular los números primos menores o iguales que n
Home-page: UNKNOWN
Author: Catalina Molina
Author-email: catalina.molina.brunet@gmail.com
License: GNU GPLv3
Keywords: numeros_primos prime number mathematical
Platform: UNKNOWN
Classifier: Development Status :: 4 - Beta
Classifier: Intended Audience :: Developers
Classifier: Topic :: Utilities
Classifier: License :: OSI Approved :: GNU General Public License v3 (GPLv3)
Classifier: Programming Language :: Python :: 3
Classifier: Operating System :: OS Independent
